datavitals/__init__.py
datavitals/cleaning.py
datavitals/etl.py
datavitals/sql_builder.py
datavitals-0.1.6.dist-info/licenses/LICENSE
datavitals-0.1.6.dist-info/METADATA
datavitals-0.1.6.dist-info/WHEEL
datavitals-0.1.6.dist-info/top_level.txt
datavitals-0.1.6.dist-info/RECORD
