Metadata-Version: 2.4
Name: datavitals
Version: 0.1.6
Summary: A reusable Python library for data cleaning, ETL pipelines, and SQL query building
Home-page: https://github.com/kamaleshkumaroffi/datavitals
Author: Kamaleshkumar.K
Author-email: kamaleshkumaroffi@gmail.com
License: MIT
Project-URL: Source, https://github.com/kamaleshkumaroffi/datavitals
Project-URL: Tracker, https://github.com/kamaleshkumaroffi/datavitals/issues
Project-URL: LinkedIn, https://www.linkedin.com/in/kamaleshkumaroffi
Keywords: data-engineering,etl,data-cleaning,sql-builder,pandas,python-library
Classifier: Programming Language :: Python :: 3
Classifier: Programming Language :: Python :: 3 :: Only
Classifier: License :: OSI Approved :: MIT License
Classifier: Operating System :: OS Independent
Classifier: Intended Audience :: Developers
Classifier: Intended Audience :: Information Technology
Classifier: Topic :: Software Development :: Libraries
Classifier: Topic :: Database
Classifier: Topic :: Scientific/Engineering :: Information Analysis
Requires-Python: >=3.8
License-File: LICENSE
Requires-Dist: pandas>=1.5.0
Provides-Extra: dev
Requires-Dist: pytest>=7.0.0; extra == "dev"
Dynamic: author
Dynamic: author-email
Dynamic: classifier
Dynamic: description
Dynamic: description-content-type
Dynamic: home-page
Dynamic: keywords
Dynamic: license
Dynamic: license-file
Dynamic: project-url
Dynamic: provides-extra
Dynamic: requires-dist
Dynamic: requires-python
Dynamic: summary
